{
  "src": "/allsrites.png",
  "alphaThr": 20,
  "rows": [
    {
      "row": 1,
      "y0": 82,
      "y1": 155,
      "frames": [
        {
          "key": "row1_col0",
          "framePath": "/sprites/custom_weapons/frames/row1_col0.png",
          "x": 51,
          "y": 81,
          "w": 85,
          "h": 76
        },
        {
          "key": "row1_col1",
          "framePath": "/sprites/custom_weapons/frames/row1_col1.png",
          "x": 164,
          "y": 94,
          "w": 152,
          "h": 63
        },
        {
          "key": "row1_col2",
          "framePath": "/sprites/custom_weapons/frames/row1_col2.png",
          "x": 342,
          "y": 88,
          "w": 107,
          "h": 62
        },
        {
          "key": "row1_col3",
          "framePath": "/sprites/custom_weapons/frames/row1_col3.png",
          "x": 497,
          "y": 90,
          "w": 82,
          "h": 54
        },
        {
          "key": "row1_col4",
          "framePath": "/sprites/custom_weapons/frames/row1_col4.png",
          "x": 591,
          "y": 90,
          "w": 104,
          "h": 64
        },
        {
          "key": "row1_col5",
          "framePath": "/sprites/custom_weapons/frames/row1_col5.png",
          "x": 707,
          "y": 81,
          "w": 100,
          "h": 76
        },
        {
          "key": "row1_col6",
          "framePath": "/sprites/custom_weapons/frames/row1_col6.png",
          "x": 831,
          "y": 81,
          "w": 141,
          "h": 76
        }
      ]
    },
    {
      "row": 2,
      "y0": 197,
      "y1": 265,
      "frames": [
        {
          "key": "row2_col0",
          "framePath": "/sprites/custom_weapons/frames/row2_col0.png",
          "x": 53,
          "y": 196,
          "w": 84,
          "h": 71
        },
        {
          "key": "row2_col1",
          "framePath": "/sprites/custom_weapons/frames/row2_col1.png",
          "x": 166,
          "y": 196,
          "w": 150,
          "h": 71
        },
        {
          "key": "row2_col2",
          "framePath": "/sprites/custom_weapons/frames/row2_col2.png",
          "x": 340,
          "y": 196,
          "w": 110,
          "h": 64
        },
        {
          "key": "row2_col3",
          "framePath": "/sprites/custom_weapons/frames/row2_col3.png",
          "x": 507,
          "y": 201,
          "w": 60,
          "h": 53
        },
        {
          "key": "row2_col4",
          "framePath": "/sprites/custom_weapons/frames/row2_col4.png",
          "x": 610,
          "y": 197,
          "w": 214,
          "h": 57
        },
        {
          "key": "row2_col5",
          "framePath": "/sprites/custom_weapons/frames/row2_col5.png",
          "x": 843,
          "y": 196,
          "w": 137,
          "h": 71
        }
      ]
    },
    {
      "row": 3,
      "y0": 306,
      "y1": 368,
      "frames": [
        {
          "key": "row3_col0",
          "framePath": "/sprites/custom_weapons/frames/row3_col0.png",
          "x": 50,
          "y": 305,
          "w": 90,
          "h": 65
        },
        {
          "key": "row3_col1",
          "framePath": "/sprites/custom_weapons/frames/row3_col1.png",
          "x": 159,
          "y": 305,
          "w": 156,
          "h": 65
        },
        {
          "key": "row3_col2",
          "framePath": "/sprites/custom_weapons/frames/row3_col2.png",
          "x": 349,
          "y": 305,
          "w": 98,
          "h": 65
        },
        {
          "key": "row3_col3",
          "framePath": "/sprites/custom_weapons/frames/row3_col3.png",
          "x": 474,
          "y": 306,
          "w": 54,
          "h": 59
        },
        {
          "key": "row3_col4",
          "framePath": "/sprites/custom_weapons/frames/row3_col4.png",
          "x": 555,
          "y": 316,
          "w": 78,
          "h": 48
        },
        {
          "key": "row3_col5",
          "framePath": "/sprites/custom_weapons/frames/row3_col5.png",
          "x": 656,
          "y": 308,
          "w": 56,
          "h": 61
        },
        {
          "key": "row3_col6",
          "framePath": "/sprites/custom_weapons/frames/row3_col6.png",
          "x": 747,
          "y": 310,
          "w": 71,
          "h": 60
        },
        {
          "key": "row3_col7",
          "framePath": "/sprites/custom_weapons/frames/row3_col7.png",
          "x": 857,
          "y": 305,
          "w": 118,
          "h": 65
        }
      ]
    },
    {
      "row": 4,
      "y0": 410,
      "y1": 481,
      "frames": [
        {
          "key": "row4_col0",
          "framePath": "/sprites/custom_weapons/frames/row4_col0.png",
          "x": 50,
          "y": 409,
          "w": 90,
          "h": 74
        },
        {
          "key": "row4_col1",
          "framePath": "/sprites/custom_weapons/frames/row4_col1.png",
          "x": 163,
          "y": 409,
          "w": 151,
          "h": 74
        },
        {
          "key": "row4_col2",
          "framePath": "/sprites/custom_weapons/frames/row4_col2.png",
          "x": 341,
          "y": 409,
          "w": 104,
          "h": 71
        },
        {
          "key": "row4_col3",
          "framePath": "/sprites/custom_weapons/frames/row4_col3.png",
          "x": 478,
          "y": 423,
          "w": 119,
          "h": 44
        },
        {
          "key": "row4_col4",
          "framePath": "/sprites/custom_weapons/frames/row4_col4.png",
          "x": 632,
          "y": 416,
          "w": 86,
          "h": 54
        },
        {
          "key": "row4_col5",
          "framePath": "/sprites/custom_weapons/frames/row4_col5.png",
          "x": 728,
          "y": 418,
          "w": 100,
          "h": 62
        },
        {
          "key": "row4_col6",
          "framePath": "/sprites/custom_weapons/frames/row4_col6.png",
          "x": 853,
          "y": 409,
          "w": 127,
          "h": 74
        }
      ]
    },
    {
      "row": 5,
      "y0": 522,
      "y1": 587,
      "frames": [
        {
          "key": "row5_col0",
          "framePath": "/sprites/custom_weapons/frames/row5_col0.png",
          "x": 51,
          "y": 521,
          "w": 89,
          "h": 68
        },
        {
          "key": "row5_col1",
          "framePath": "/sprites/custom_weapons/frames/row5_col1.png",
          "x": 159,
          "y": 522,
          "w": 159,
          "h": 67
        },
        {
          "key": "row5_col2",
          "framePath": "/sprites/custom_weapons/frames/row5_col2.png",
          "x": 342,
          "y": 521,
          "w": 65,
          "h": 66
        },
        {
          "key": "row5_col3",
          "framePath": "/sprites/custom_weapons/frames/row5_col3.png",
          "x": 419,
          "y": 521,
          "w": 75,
          "h": 68
        },
        {
          "key": "row5_col4",
          "framePath": "/sprites/custom_weapons/frames/row5_col4.png",
          "x": 524,
          "y": 525,
          "w": 238,
          "h": 64
        },
        {
          "key": "row5_col5",
          "framePath": "/sprites/custom_weapons/frames/row5_col5.png",
          "x": 770,
          "y": 521,
          "w": 72,
          "h": 68
        },
        {
          "key": "row5_col6",
          "framePath": "/sprites/custom_weapons/frames/row5_col6.png",
          "x": 860,
          "y": 521,
          "w": 123,
          "h": 68
        }
      ]
    },
    {
      "row": 6,
      "y0": 635,
      "y1": 705,
      "frames": [
        {
          "key": "row6_col0",
          "framePath": "/sprites/custom_weapons/frames/row6_col0.png",
          "x": 51,
          "y": 634,
          "w": 86,
          "h": 73
        },
        {
          "key": "row6_col1",
          "framePath": "/sprites/custom_weapons/frames/row6_col1.png",
          "x": 159,
          "y": 634,
          "w": 160,
          "h": 73
        },
        {
          "key": "row6_col2",
          "framePath": "/sprites/custom_weapons/frames/row6_col2.png",
          "x": 342,
          "y": 653,
          "w": 31,
          "h": 28
        },
        {
          "key": "row6_col3",
          "framePath": "/sprites/custom_weapons/frames/row6_col3.png",
          "x": 391,
          "y": 634,
          "w": 431,
          "h": 73
        },
        {
          "key": "row6_col4",
          "framePath": "/sprites/custom_weapons/frames/row6_col4.png",
          "x": 839,
          "y": 634,
          "w": 149,
          "h": 73
        }
      ]
    },
    {
      "row": 7,
      "y0": 741,
      "y1": 816,
      "frames": [
        {
          "key": "row7_col0",
          "framePath": "/sprites/custom_weapons/frames/row7_col0.png",
          "x": 50,
          "y": 740,
          "w": 87,
          "h": 78
        },
        {
          "key": "row7_col1",
          "framePath": "/sprites/custom_weapons/frames/row7_col1.png",
          "x": 165,
          "y": 741,
          "w": 70,
          "h": 77
        },
        {
          "key": "row7_col2",
          "framePath": "/sprites/custom_weapons/frames/row7_col2.png",
          "x": 250,
          "y": 741,
          "w": 69,
          "h": 77
        },
        {
          "key": "row7_col3",
          "framePath": "/sprites/custom_weapons/frames/row7_col3.png",
          "x": 348,
          "y": 740,
          "w": 72,
          "h": 64
        },
        {
          "key": "row7_col4",
          "framePath": "/sprites/custom_weapons/frames/row7_col4.png",
          "x": 429,
          "y": 742,
          "w": 142,
          "h": 63
        },
        {
          "key": "row7_col5",
          "framePath": "/sprites/custom_weapons/frames/row7_col5.png",
          "x": 570,
          "y": 740,
          "w": 142,
          "h": 76
        },
        {
          "key": "row7_col6",
          "framePath": "/sprites/custom_weapons/frames/row7_col6.png",
          "x": 730,
          "y": 746,
          "w": 102,
          "h": 72
        },
        {
          "key": "row7_col7",
          "framePath": "/sprites/custom_weapons/frames/row7_col7.png",
          "x": 849,
          "y": 740,
          "w": 144,
          "h": 78
        }
      ]
    },
    {
      "row": 8,
      "y0": 854,
      "y1": 917,
      "frames": [
        {
          "key": "row8_col0",
          "framePath": "/sprites/custom_weapons/frames/row8_col0.png",
          "x": 51,
          "y": 853,
          "w": 94,
          "h": 66
        },
        {
          "key": "row8_col1",
          "framePath": "/sprites/custom_weapons/frames/row8_col1.png",
          "x": 160,
          "y": 856,
          "w": 143,
          "h": 63
        },
        {
          "key": "row8_col2",
          "framePath": "/sprites/custom_weapons/frames/row8_col2.png",
          "x": 326,
          "y": 860,
          "w": 94,
          "h": 41
        },
        {
          "key": "row8_col3",
          "framePath": "/sprites/custom_weapons/frames/row8_col3.png",
          "x": 469,
          "y": 866,
          "w": 43,
          "h": 35
        },
        {
          "key": "row8_col4",
          "framePath": "/sprites/custom_weapons/frames/row8_col4.png",
          "x": 523,
          "y": 862,
          "w": 90,
          "h": 41
        },
        {
          "key": "row8_col5",
          "framePath": "/sprites/custom_weapons/frames/row8_col5.png",
          "x": 648,
          "y": 853,
          "w": 73,
          "h": 61
        },
        {
          "key": "row8_col6",
          "framePath": "/sprites/custom_weapons/frames/row8_col6.png",
          "x": 751,
          "y": 853,
          "w": 83,
          "h": 66
        },
        {
          "key": "row8_col7",
          "framePath": "/sprites/custom_weapons/frames/row8_col7.png",
          "x": 855,
          "y": 853,
          "w": 130,
          "h": 66
        }
      ]
    },
    {
      "row": 9,
      "y0": 960,
      "y1": 1026,
      "frames": [
        {
          "key": "row9_col0",
          "framePath": "/sprites/custom_weapons/frames/row9_col0.png",
          "x": 50,
          "y": 959,
          "w": 91,
          "h": 69
        },
        {
          "key": "row9_col1",
          "framePath": "/sprites/custom_weapons/frames/row9_col1.png",
          "x": 163,
          "y": 961,
          "w": 138,
          "h": 67
        },
        {
          "key": "row9_col2",
          "framePath": "/sprites/custom_weapons/frames/row9_col2.png",
          "x": 337,
          "y": 959,
          "w": 313,
          "h": 69
        },
        {
          "key": "row9_col3",
          "framePath": "/sprites/custom_weapons/frames/row9_col3.png",
          "x": 670,
          "y": 965,
          "w": 113,
          "h": 57
        },
        {
          "key": "row9_col4",
          "framePath": "/sprites/custom_weapons/frames/row9_col4.png",
          "x": 792,
          "y": 959,
          "w": 60,
          "h": 62
        },
        {
          "key": "row9_col5",
          "framePath": "/sprites/custom_weapons/frames/row9_col5.png",
          "x": 860,
          "y": 959,
          "w": 135,
          "h": 69
        }
      ]
    },
    {
      "row": 10,
      "y0": 1067,
      "y1": 1137,
      "frames": [
        {
          "key": "row10_col0",
          "framePath": "/sprites/custom_weapons/frames/row10_col0.png",
          "x": 50,
          "y": 1066,
          "w": 90,
          "h": 73
        },
        {
          "key": "row10_col1",
          "framePath": "/sprites/custom_weapons/frames/row10_col1.png",
          "x": 157,
          "y": 1072,
          "w": 112,
          "h": 63
        },
        {
          "key": "row10_col2",
          "framePath": "/sprites/custom_weapons/frames/row10_col2.png",
          "x": 288,
          "y": 1070,
          "w": 47,
          "h": 57
        },
        {
          "key": "row10_col3",
          "framePath": "/sprites/custom_weapons/frames/row10_col3.png",
          "x": 593,
          "y": 1066,
          "w": 88,
          "h": 73
        },
        {
          "key": "row10_col4",
          "framePath": "/sprites/custom_weapons/frames/row10_col4.png",
          "x": 703,
          "y": 1066,
          "w": 37,
          "h": 64
        },
        {
          "key": "row10_col5",
          "framePath": "/sprites/custom_weapons/frames/row10_col5.png",
          "x": 755,
          "y": 1066,
          "w": 39,
          "h": 60
        },
        {
          "key": "row10_col6",
          "framePath": "/sprites/custom_weapons/frames/row10_col6.png",
          "x": 857,
          "y": 1066,
          "w": 123,
          "h": 73
        }
      ]
    },
    {
      "row": 11,
      "y0": 1173,
      "y1": 1255,
      "frames": [
        {
          "key": "row11_col0",
          "framePath": "/sprites/custom_weapons/frames/row11_col0.png",
          "x": 50,
          "y": 1172,
          "w": 91,
          "h": 84
        },
        {
          "key": "row11_col1",
          "framePath": "/sprites/custom_weapons/frames/row11_col1.png",
          "x": 162,
          "y": 1172,
          "w": 98,
          "h": 80
        },
        {
          "key": "row11_col2",
          "framePath": "/sprites/custom_weapons/frames/row11_col2.png",
          "x": 275,
          "y": 1189,
          "w": 43,
          "h": 46
        },
        {
          "key": "row11_col3",
          "framePath": "/sprites/custom_weapons/frames/row11_col3.png",
          "x": 336,
          "y": 1177,
          "w": 49,
          "h": 73
        },
        {
          "key": "row11_col4",
          "framePath": "/sprites/custom_weapons/frames/row11_col4.png",
          "x": 409,
          "y": 1173,
          "w": 112,
          "h": 84
        },
        {
          "key": "row11_col5",
          "framePath": "/sprites/custom_weapons/frames/row11_col5.png",
          "x": 537,
          "y": 1172,
          "w": 108,
          "h": 85
        },
        {
          "key": "row11_col6",
          "framePath": "/sprites/custom_weapons/frames/row11_col6.png",
          "x": 670,
          "y": 1172,
          "w": 145,
          "h": 85
        },
        {
          "key": "row11_col7",
          "framePath": "/sprites/custom_weapons/frames/row11_col7.png",
          "x": 850,
          "y": 1172,
          "w": 135,
          "h": 85
        }
      ]
    }
  ]
}